cpcr/__init__.py
cpcr/_version.py
cpcr/run.py
tests/__init__.py
tests/context.py
tests/test_clermontpcr.py
webapp/__init__.py
webapp/clermontwebapp.py
ezclermont-0.7.0.dist-info/LICENSE
ezclermont-0.7.0.dist-info/METADATA
ezclermont-0.7.0.dist-info/WHEEL
ezclermont-0.7.0.dist-info/entry_points.txt
ezclermont-0.7.0.dist-info/top_level.txt
ezclermont-0.7.0.dist-info/RECORD
