Metadata-Version: 2.1
Name: ezclermont
Version: 0.7.0
Summary: ezclermont: phylotype your E. coli strains, in silico
Home-page: https://github.com/nickp60/EzClermont
Author: Nick Waters
Author-email: nickp60@gmail.com
License: MIT
Keywords: bioinformatics evolution genomics development
Platform: UNKNOWN
Classifier: Development Status :: 3 - Alpha
Classifier: Intended Audience :: Developers
Classifier: Intended Audience :: Science/Research
Classifier: Topic :: Scientific/Engineering :: Bio-Informatics
Classifier: License :: OSI Approved :: MIT License
Classifier: Programming Language :: Python :: 3.5
Classifier: Programming Language :: Python :: 3.6
Classifier: Programming Language :: Python :: 3.7
Classifier: Programming Language :: Python :: 3.8
License-File: LICENSE
Requires-Dist: Biopython
Requires-Dist: coverage
